word_count_mcp/__init__.py
word_count_mcp/__main__.py
word_count_mcp/server.py
word_count_mcp-0.1.5.dist-info/METADATA
word_count_mcp-0.1.5.dist-info/WHEEL
word_count_mcp-0.1.5.dist-info/entry_points.txt
word_count_mcp-0.1.5.dist-info/top_level.txt
word_count_mcp-0.1.5.dist-info/RECORD
