Metadata-Version: 2.4
Name: word_count_mcp
Version: 0.1.5
Summary: MCP 工具：统计一句话的字数
License: MIT
Keywords: mcp,wordcount
Classifier: Programming Language :: Python :: 3
Classifier: License :: OSI Approved :: MIT License
Classifier: Operating System :: OS Independent
Requires-Python: >=3.8
Requires-Dist: mcp>=0.1.0
